castepinput/__init__.py
castepinput/common.py
castepinput/inputs.py
castepinput/parser.py
castepinput-0.1.10.dist-info/LICENSE
castepinput-0.1.10.dist-info/WHEEL
castepinput-0.1.10.dist-info/METADATA
castepinput-0.1.10.dist-info/RECORD
