Metadata-Version: 2.1
Name: castepinput
Version: 0.1.10
Summary: Base module of castepinput
Author-email: Bonan Zhu <zhubonan@outlook.com>
Requires-Python: >=3.8
Classifier: License :: OSI Approved :: MIT License
Classifier: Programming Language :: Python :: 3.8
Classifier: Programming Language :: Python :: 3.9
Classifier: Programming Language :: Python :: 3.10
Classifier: Programming Language :: Python :: 3.11
Classifier: Development Status :: 4 - Beta
Requires-Dist: numpy
Requires-Dist: pre-commit ; extra == "pre-commit"
Requires-Dist: pylint-pytest ; extra == "pre-commit"
Requires-Dist: pytest ; extra == "test"
Requires-Dist: pytest-cov ; extra == "test"
Requires-Dist: coverage ; extra == "test"
Project-URL: Home, https://github.com/zhubonan/castepinput
Provides-Extra: pre-commit
Provides-Extra: test
